mypy_boto3_cloudwatch/__init__.py
mypy_boto3_cloudwatch/__init__.pyi
mypy_boto3_cloudwatch/__main__.py
mypy_boto3_cloudwatch/client.py
mypy_boto3_cloudwatch/client.pyi
mypy_boto3_cloudwatch/literals.py
mypy_boto3_cloudwatch/literals.pyi
mypy_boto3_cloudwatch/paginator.py
mypy_boto3_cloudwatch/paginator.pyi
mypy_boto3_cloudwatch/py.typed
mypy_boto3_cloudwatch/service_resource.py
mypy_boto3_cloudwatch/service_resource.pyi
mypy_boto3_cloudwatch/type_defs.py
mypy_boto3_cloudwatch/type_defs.pyi
mypy_boto3_cloudwatch/version.py
mypy_boto3_cloudwatch/waiter.py
mypy_boto3_cloudwatch/waiter.pyi
mypy_boto3_cloudwatch-1.40.38.dist-info/licenses/LICENSE
mypy_boto3_cloudwatch-1.40.38.dist-info/METADATA
mypy_boto3_cloudwatch-1.40.38.dist-info/WHEEL
mypy_boto3_cloudwatch-1.40.38.dist-info/top_level.txt
mypy_boto3_cloudwatch-1.40.38.dist-info/RECORD
